growcube_client/__init__.py
growcube_client/growcubeclient.py
growcube_client/growcubecommand.py
growcube_client/growcubediscovery.py
growcube_client/growcubeenums.py
growcube_client/growcubemessage.py
growcube_client/growcubeprotocol.py
growcube_client/growcubereport.py
growcube_client-1.2.7.dist-info/licenses/LICENSE
growcube_client-1.2.7.dist-info/METADATA
growcube_client-1.2.7.dist-info/WHEEL
growcube_client-1.2.7.dist-info/top_level.txt
growcube_client-1.2.7.dist-info/RECORD
